[
    {
        "id": "PRODUCT-001",
        "category": "product",
        "title": "제품 목록 페이지 — 카드 그리드 + 카테고리 필터",
        "description": "/products 페이지에 전체 제품을 카드 그리드로 보여주고, 좌측 사이드바로 카테고리 필터링을 제공한다. 네비게이션 드롭다운으로 진입 시 해당 카테고리로 필터링된 목록을 보여준다.",
        "steps": [
          "/products 접속 시 공개(is_published=true) 제품 전체 카드 그리드 노출 확인",
          "좌측 사이드바 카테고리 클릭 시 해당 카테고리 제품만 필터링 확인",
          "GNB 드롭다운 서브카테고리 클릭 시 해당 카테고리로 필터링된 목록 진입 확인 (?category=slug)",
          "제품 카드 hover 인터랙션 정상 동작 확인",
          "제품 카드 클릭 시 /products/[id]로 이동 확인",
          "등록된 제품 없을 때 빈 상태 메시지 노출 확인"
        ],
        "passes": true
      },
      {
        "id": "PRODUCT-002",
        "category": "product",
        "title": "제품 상세 페이지 — 이미지 갤러리 + 상세 설명",
        "description": "/products/[id]에서 제품 대표 이미지 갤러리, 제품명, 카테고리, 간단 설명, HTML 상세 내용을 보여준다.",
        "steps": [
          "/products/[id] 접속 시 제품 정보 정상 노출 확인",
          "대표 이미지 및 추가 이미지 갤러리 썸네일 클릭 시 메인 이미지 전환 확인",
          "상세 설명 HTML 콘텐츠 정상 렌더링 확인",
          "존재하지 않는 id 접근 시 404 처리 확인",
          "모바일 반응형 레이아웃 확인"
        ],
        "passes": false
      }
]